[
  {
    "name": "Projets ICOWPEA & Proveggas",
    "desc": "Contribution en tant que stagiaire Master 2.",
    "image": "legumes1",
    "category": "Stages",
    "pdf": "/assets/Soutenance  Lorène AKISSOE-Master 2 PVIA-finale"
  },
  {
    "name": "Projet PNCA",
    "desc": "Contribution en tant que stagiaire Master 1",
    "image": "lait1",
    "category": "Stages",
    "links": {
      "view": "https://github.com/lakissoe/Stage-M1.git",
      "code": "#"
    }
  },
  {
    "name": "Projet TransNut Niébé",
    "desc": "Ma thèse",
    "image": "legumes2",
    "category": "Expérience professionnelle",
    "links": {
      "view": "https://github.com/lakissoe/Ma-th-se.git",
      "code": "#"
    }
  },
  {
    "name": "Projet AGAPE",
    "desc": "Contribution en tant que Chargée de projet R&D Innovation Produits",
    "image": "AGAPE",
    "category": "Expériences Professionnelles",
    "links": {
      "view": "https://github.com/lakissoe/AGAPE.git",
      "code": "#"
    }
  },
  {
    "name": "Projet FAN",
    "desc": "Contribution en tant que Chargée de projet en biochimie & sciences des aliments",
    "image": "Nutriset",
    "category": "Expériences Professionnelles",
    "links": {
      "view": "https://github.com/lakissoe/ProjetFan.git",
      "code": "#"
    }
  }

]
